[
  {
    "_id": "0495afdf-f071-424d-9432-1b3471b2616c",
    "name": "Instawork",
    "domains": ["instawork.com"],
    "description": "The flexible work platform that connects local businesses with a network of over 7 million skilled hourly workers",
    "primary_location": {"city": "San Francisco", "state": "California", "country": "United States"},
    "linkedin": "instawork",
    "employee_range": "1K-5K",
    "_created_at": "2026-01-29T12:16:25Z",
    "_updated_at": "2026-01-29T14:49:33Z"
  },
  {
    "_id": "374752e9-7b86-4ada-9837-81e3e39ab5cf",
    "name": "Constructive Dialogue Institute",
    "domains": ["constructivedialogue.org"],
    "description": "A scalable, evidence-based approach to constructive dialogue",
    "primary_location": {"state": "New York", "country": "United States"},
    "linkedin": "openmind-platform",
    "employee_range": "11-50",
    "_created_at": "2026-01-29T10:23:11Z",
    "_updated_at": "2026-01-29T10:23:13Z"
  },
  {
    "_id": "10d6e943-c23e-4156-b9d8-9d054cad651f",
    "name": "Rhyoline Professional Corporation",
    "domains": ["rhyoline.com"],
    "linkedin": "rhyoline-professional-corporation",
    "employee_range": "1-10",
    "_created_at": "2026-01-26T07:22:09Z",
    "_updated_at": "2026-01-26T08:21:56Z"
  },
  {
    "_id": "c65291f5-659c-4263-a7da-9f31f710c828",
    "name": "Glean",
    "domains": ["glean.com"],
    "description": "The Work AI platform connected to all your company data. Find, create, and automate anything.",
    "primary_location": {"city": "Palo Alto", "state": "California", "country": "United States"},
    "linkedin": "gleanwork",
    "employee_range": "251-1K",
    "_created_at": "2026-01-23T16:58:33Z",
    "_updated_at": "2026-01-29T16:09:45Z"
  },
  {
    "_id": "eabc07ab-54ee-4d99-a83d-aa5dd52f23ab",
    "name": "Eraser",
    "domains": ["eraser.io"],
    "description": "A whiteboard that lets you focus on ideas.",
    "primary_location": {"city": "San Francisco", "state": "California", "country": "United States"},
    "linkedin": "eraser",
    "employee_range": "11-50",
    "_created_at": "2026-01-23T12:16:21Z",
    "_updated_at": "2026-01-26T10:00:13Z"
  },
  {
    "_id": "60b02c78-b494-4610-9e00-f933793c0dbe",
    "name": "Strategic Search Solutions",
    "domains": ["strategicsearches.com"],
    "description": "Enterprise SaaS / Cloud / Software Sales Recruiters",
    "primary_location": {"city": "Carlsbad", "state": "California", "country": "United States"},
    "linkedin": "strategic-search-solutions",
    "employee_range": "1-10",
    "_created_at": "2026-01-22T11:17:05Z",
    "_updated_at": "2026-01-28T14:30:32Z"
  },
  {
    "_id": "f5e2c7ef-434a-4cdf-826e-816485fa5d6b",
    "name": "WSO2",
    "domains": ["wso2.com"],
    "description": "Create awesome digital experiences quickly, easily, and securely with WSO2 - just add developers",
    "primary_location": {"city": "Mountain View", "state": "California", "country": "United States"},
    "linkedin": "wso2",
    "employee_range": "1K-5K",
    "_created_at": "2026-01-22T11:16:27Z",
    "_updated_at": "2026-01-28T14:30:32Z"
  },
  {
    "_id": "80a82c06-d05c-4be2-b277-448f295c8f0a",
    "name": "Insightscompany",
    "domains": ["insightscompany.io"],
    "_created_at": "2026-01-22T07:25:30Z",
    "_updated_at": "2026-01-28T10:20:52Z"
  },
  {
    "_id": "fa2cf97b-7bb6-4894-8e04-9ec8108a4c9d",
    "name": "NewGTM.ai",
    "domains": ["newgtm.ai"],
    "description": "AI GTM Engine that does the work of 5-10 BDRs working 24/7",
    "primary_location": {"city": "Bernardsville", "state": "New Jersey", "country": "United States"},
    "linkedin": "newgtm-ai",
    "employee_range": "1-10",
    "_created_at": "2026-01-21T09:08:44Z",
    "_updated_at": "2026-01-27T16:21:05Z"
  },
  {
    "_id": "662b540f-1d5a-4a2f-a5b8-815b48886450",
    "name": "Atomicfi",
    "domains": ["atomicfi.com"],
    "description": "Atomic is a financial technology company that provides innovative solutions for digital banking and financial services.",
    "primary_location": {"state": "Utah", "country": "United States"},
    "_created_at": "2026-01-19T22:01:32Z",
    "_updated_at": "2026-01-20T09:08:22Z"
  },
  {
    "_id": "150db110-59c2-4330-82ae-7b5aebc69cf7",
    "name": "Freckle",
    "domains": ["freckle.io"],
    "description": "The Clay-alternative built for non-technical users",
    "linkedin": "freckleio",
    "employee_range": "1-10",
    "_created_at": "2026-01-19T07:59:39Z",
    "_updated_at": "2026-01-19T07:59:42Z"
  },
  {
    "_id": "2d9aa33b-a798-4a39-81a0-f9cbb525e238",
    "name": "Saltmine",
    "domains": ["saltmine.com"],
    "description": "All-in-one Enterprise Workplace Platform",
    "primary_location": {"city": "San Francisco", "state": "California", "country": "United States"},
    "linkedin": "saltmine1",
    "employee_range": "51-250",
    "_created_at": "2026-01-18T22:56:16Z",
    "_updated_at": "2026-01-20T09:08:21Z"
  },
  {
    "_id": "1b7fe70e-9c2a-4b71-a201-724bfa8892c0",
    "name": "Monitor ML",
    "domains": ["arize.com"],
    "description": "Real-time production monitoring of ML models, made simple.",
    "linkedin": "monitor-ml",
    "employee_range": "1-10",
    "_created_at": "2026-01-16T18:27:09Z",
    "_updated_at": "2026-01-20T09:08:25Z"
  },
  {
    "_id": "87aae853-0379-46f9-bf6c-3fcb665210a0",
    "name": "DataGravity",
    "domains": ["anomalo.com"],
    "description": "Anomalo's Data Quality Software uses automated AI to detect data quality issues and understand their root causes.",
    "primary_location": {"city": "Nashua", "state": "New Hampshire", "country": "United States"},
    "linkedin": "datagravity",
    "employee_range": "1-10",
    "_created_at": "2026-01-16T18:27:09Z",
    "_updated_at": "2026-01-20T09:08:21Z"
  },
  {
    "_id": "b1ccf58c-ce01-4334-8d20-e5e80cec8477",
    "name": "Ironclad",
    "domains": ["ironcladhq.com"],
    "description": "Ironclad is the global leader in AI-powered contract management software.",
    "primary_location": {"city": "San Francisco", "state": "California", "country": "United States"},
    "linkedin": "ironclad-inc-",
    "estimated_arr": "$50M-$100M",
    "employee_range": "251-1K",
    "_created_at": "2026-01-16T18:27:09Z",
    "_updated_at": "2026-01-20T09:08:21Z"
  },
  {
    "_id": "7ff74584-39b9-4b3c-b4dc-a5397439d8a2",
    "name": "Pano AI",
    "domains": ["pano.ai"],
    "description": "The leader in early wildfire detection and actionable intelligence",
    "primary_location": {"city": "San Francisco", "state": "California", "country": "United States"},
    "linkedin": "pano-ai",
    "employee_range": "51-250",
    "_created_at": "2026-01-16T18:27:09Z",
    "_updated_at": "2026-01-20T09:08:22Z"
  },
  {
    "_id": "fb4a0986-25df-48f0-b320-979f8c2ee485",
    "name": "Clarify",
    "domains": ["clarify.ai"],
    "description": "Clarify is an AI-native customer relationship management (CRM) company based in Seattle.",
    "primary_location": {"city": "Seattle", "state": "Washington", "country": "United States"},
    "linkedin": "getclarify",
    "employee_range": "11-50",
    "_created_at": "2026-01-12T11:27:29Z",
    "_updated_at": "2026-01-16T20:00:38Z"
  },
  {
    "_id": "5350f806-be40-4925-9625-46c401132427",
    "name": "Creatorbuzz",
    "domains": ["creatorbuzz.com"],
    "description": "B2B influencer marketing company.",
    "linkedin": "creatorbuzz",
    "employee_range": "1-10",
    "_created_at": "2026-01-12T09:48:08Z",
    "_updated_at": "2026-01-21T04:01:05Z"
  },
  {
    "_id": "5ccd1a78-56c3-4229-a868-6633551ec43c",
    "name": "Apollomail",
    "domains": ["apollomail.io"],
    "_created_at": "2026-01-11T13:59:40Z",
    "_updated_at": "2026-01-13T17:03:49Z"
  },
  {
    "_id": "cd96618c-c3da-4740-9d8d-0b402674c84c",
    "name": "Candidly",
    "domains": ["getcandidly.com"],
    "description": "Financial wellness company focusing on student debt and education expense management.",
    "primary_location": {"city": "New York", "state": "New York", "country": "United States"},
    "linkedin": "getcandidly",
    "estimated_arr": "1.2M",
    "employee_range": "51-250",
    "_created_at": "2026-01-09T09:12:14Z",
    "_updated_at": "2026-01-13T16:18:03Z"
  },
  {
    "_id": "55861343-e267-4371-8763-7c6519b08bed",
    "name": "Apollo.io",
    "domains": ["apollo.io"],
    "description": "Apollo.io is a sales intelligence platform with a database of over 275 million contacts and 73 million companies.",
    "primary_location": {"city": "San Francisco", "state": "California", "country": "United States"},
    "linkedin": "apolloio",
    "estimated_arr": "$50M-$100M",
    "employee_range": "251-1K",
    "_created_at": "2026-01-06T11:07:11Z",
    "_updated_at": "2026-01-28T11:24:59Z"
  },
  {
    "_id": "84a66d00-35ad-4243-8d95-d8ae83f079bf",
    "name": "Attio",
    "domains": ["attio.com"],
    "description": "The CRM of the future.",
    "primary_location": {"city": "London", "state": "Greater London", "country": "United Kingdom"},
    "linkedin": "attio",
    "employee_range": "51-250",
    "_created_at": "2026-01-06T07:40:01Z",
    "_updated_at": "2026-01-13T16:18:03Z"
  },
  {
    "_id": "687a5204-6809-4465-ac18-a903be71087a",
    "name": "Health Recovery Solutions",
    "domains": ["healthrecoverysolutions.com"],
    "description": "Advanced Remote Patient Monitoring & Telehealth Solutions",
    "primary_location": {"city": "Hoboken", "state": "New Jersey", "country": "United States"},
    "linkedin": "health-recovery-solutions",
    "employee_range": "51-250",
    "_created_at": "2025-12-30T08:35:21Z",
    "_updated_at": "2025-12-30T16:16:44Z"
  },
  {
    "_id": "19d89667-9690-4ed2-b766-454bbffe4f46",
    "name": "Ansrsource",
    "domains": ["ansrsource.com"],
    "description": "Accelerating Better Ways to Learn",
    "primary_location": {"city": "Austin", "state": "Texas", "country": "United States"},
    "linkedin": "ansrsource",
    "employee_range": "251-1K",
    "_created_at": "2025-12-18T10:57:53Z",
    "_updated_at": "2026-01-05T09:55:45Z"
  },
  {
    "_id": "56525d92-1e3b-4b65-9f2b-b3526c2ab9fd",
    "name": "SNAPS",
    "domains": ["snaps.ltd"],
    "description": "Developing innovative products that grow the game of golf.",
    "primary_location": {"city": "Jupiter", "state": "Florida", "country": "United States"},
    "linkedin": "snaps-golf",
    "employee_range": "11-50",
    "_created_at": "2025-12-15T08:53:43Z",
    "_updated_at": "2026-01-22T07:40:54Z"
  },
  {
    "_id": "50d15c77-2af5-4ae4-a53e-b97d87081eeb",
    "name": "HeyReach.io",
    "domains": ["heyreach.io"],
    "description": "LinkedIn automation platform for lead generation agencies and sales teams.",
    "primary_location": {"city": "Skopje", "state": "Greater Skopje", "country": "North Macedonia"},
    "linkedin": "heyreachio",
    "employee_range": "51-250",
    "_created_at": "2025-12-13T14:05:42Z",
    "_updated_at": "2025-12-23T15:40:00Z"
  },
  {
    "_id": "e72748a9-32f1-4ada-b0d5-1a7ecd9398c6",
    "name": "Ambient.ai",
    "domains": ["ambient.ai"],
    "description": "Computer vision intelligence and AI company transforming enterprise security operations.",
    "primary_location": {"city": "Palo Alto", "state": "California", "country": "United States"},
    "linkedin": "ambient-ai",
    "employee_range": "51-250",
    "_created_at": "2025-12-09T07:51:27Z",
    "_updated_at": "2025-12-11T11:05:28Z"
  },
  {
    "_id": "d9881d61-3a92-4816-b3c3-35ab350b81a6",
    "name": "Salesforce",
    "domains": ["salesforce.com"],
    "description": "Top enterprise cloud computing and CRM provider.",
    "primary_location": {"city": "San Francisco", "state": "California", "country": "United States"},
    "linkedin": "salesforce",
    "estimated_arr": "$10B+",
    "employee_range": "50K-100K",
    "_created_at": "2025-12-08T06:45:40Z",
    "_updated_at": "2026-01-20T09:08:22Z"
  },
  {
    "_id": "03841acf-8930-49c0-a31e-9375674df0c7",
    "name": "Uplimit",
    "domains": ["uplimit.com"],
    "description": "The AI-native learning platform",
    "employee_range": "51-250",
    "_created_at": "2025-12-08T05:34:32Z",
    "_updated_at": "2025-12-08T16:15:55Z"
  },
  {
    "_id": "1ea0e774-b58a-4ed2-939c-630ec7026a08",
    "name": "Flagler Health",
    "domains": ["flaglerhealth.io"],
    "description": "We help turn clinics into virtual health systems",
    "primary_location": {"city": "New York", "state": "New York", "country": "United States"},
    "linkedin": "flagler-health",
    "employee_range": "11-50",
    "_created_at": "2025-12-03T08:23:26Z",
    "_updated_at": "2026-01-06T14:21:02Z"
  },
  {
    "_id": "aa63df64-2a1c-4779-a8aa-a74414fcd647",
    "name": "eSmart Systems",
    "domains": ["esmartsystems.com"],
    "description": "Grid Vision built by eSmart Systems transforms how utilities inspect and maintain critical infrastructure.",
    "primary_location": {"city": "Halden", "state": "Ostfold", "country": "Norway"},
    "linkedin": "esmart-systems",
    "employee_range": "51-250",
    "_created_at": "2025-11-07T10:13:43Z",
    "_updated_at": "2026-01-27T13:37:39Z"
  },
  {
    "_id": "e6a5297e-981b-4d32-847a-98437b558299",
    "name": "SalesRoads",
    "domains": ["salesroads.com"],
    "description": "America's leading B2B appointment setting and lead generation provider.",
    "primary_location": {"city": "Coral Springs", "state": "Florida", "country": "United States"},
    "linkedin": "salesroads",
    "estimated_arr": "$10M-$50M",
    "employee_range": "51-250",
    "_created_at": "2025-11-07T06:25:51Z",
    "_updated_at": "2025-12-01T10:51:37Z"
  },
  {
    "_id": "14174213-78bc-494f-b206-893e46d8ae41",
    "name": "Tines",
    "domains": ["tines.io"],
    "description": "Automation platform for security and IT teams.",
    "primary_location": {"city": "Dublin", "state": "County Dublin", "country": "Ireland"},
    "linkedin": "tines-io",
    "estimated_arr": "4.1M",
    "employee_range": "251-1K",
    "_created_at": "2025-11-10T06:56:57Z",
    "_updated_at": "2025-12-01T10:51:37Z"
  },
  {
    "_id": "5e14bbb9-d157-406c-b928-e6510c8d6ec6",
    "name": "Vultr",
    "domains": ["vultr.com"],
    "description": "High-performance cloud computing made easy and affordable.",
    "primary_location": {"city": "West Palm Beach", "state": "Florida", "country": "United States"},
    "linkedin": "vultr",
    "employee_range": "251-1K",
    "_created_at": "2025-11-10T06:56:57Z",
    "_updated_at": "2025-12-01T10:51:37Z"
  },
  {
    "_id": "ec0112d7-ca79-4476-a6dc-cb7fb228e174",
    "name": "Sayers",
    "domains": ["sayers.com"],
    "description": "Technology Solutions Built Around You",
    "primary_location": {"city": "Vernon Hills", "state": "Illinois", "country": "United States"},
    "linkedin": "sayers",
    "employee_range": "251-1K",
    "_created_at": "2025-10-23T18:15:25Z",
    "_updated_at": "2025-12-12T13:04:04Z"
  },
  {
    "_id": "ce3aea6d-0758-4429-9578-b3c9d73b2019",
    "name": "Clay",
    "domains": ["clay.com"],
    "description": "The Creative Tool for Growth",
    "primary_location": {"city": "Brooklyn", "state": "New York", "country": "United States"},
    "linkedin": "grow-with-clay",
    "employee_range": "51-250",
    "_created_at": "2025-10-23T16:23:31Z",
    "_updated_at": "2026-01-28T12:03:11Z"
  },
  {
    "_id": "c50ed8e2-0217-482b-8cca-c5ec21312b4d",
    "name": "The Deal Lab",
    "domains": ["thedeallab.com"],
    "linkedin": "thedeallab",
    "_created_at": "2025-10-23T16:23:29Z",
    "_updated_at": "2025-10-23T16:23:30Z"
  },
  {
    "_id": "51d7a703-cdc6-4f7a-8009-b9bf128a6b57",
    "name": "Wiza",
    "domains": ["wiza.com"],
    "primary_location": {"city": "Newark", "state": "Delaware", "country": "United States"},
    "linkedin": "wizainc",
    "employee_range": "11-50",
    "_created_at": "2025-10-23T16:23:28Z",
    "_updated_at": "2025-10-28T16:04:08Z"
  },
  {
    "_id": "e02b8ce9-f519-4b43-af3b-0e611f091d43",
    "name": "GUIDEcx",
    "domains": ["guidecx.com"],
    "description": "We help people work better together!",
    "primary_location": {"city": "Draper", "state": "Utah", "country": "United States"},
    "linkedin": "guidecx",
    "employee_range": "51-250",
    "_created_at": "2025-10-23T16:23:28Z",
    "_updated_at": "2025-10-23T16:23:30Z"
  },
  {
    "_id": "b689aacc-c436-44b9-8b09-596dfd899fbb",
    "name": "Octave",
    "domains": ["octavehq.com"],
    "description": "Welcome to Generative GTM",
    "primary_location": {"city": "San Francisco", "state": "California", "country": "United States"},
    "linkedin": "octavehq",
    "employee_range": "11-50",
    "_created_at": "2025-10-23T16:23:28Z",
    "_updated_at": "2025-10-23T16:23:30Z"
  },
  {
    "_id": "14c5d1bd-f8b2-4049-9ec8-fe5d49e9a599",
    "name": "Uplight",
    "domains": ["uplight.com"],
    "description": "The technology partner for energy providers and the clean energy ecosystem.",
    "primary_location": {"city": "Boulder", "state": "Colorado", "country": "United States"},
    "linkedin": "uplightenergy",
    "employee_range": "251-1K",
    "_created_at": "2025-10-23T16:23:28Z",
    "_updated_at": "2025-10-31T19:36:45Z"
  },
  {
    "_id": "5869ac10-9d62-43ca-bfdc-b7ac946258fb",
    "name": "Quote Roller",
    "domains": ["pandadoc.com"],
    "description": "PandaDoc streamlines proposals, quotes & other business document workflows.",
    "primary_location": {"city": "South San Francisco", "state": "California", "country": "United States"},
    "linkedin": "quote-roller",
    "employee_range": "1-10",
    "_created_at": "2025-10-23T16:23:28Z",
    "_updated_at": "2026-01-28T16:20:03Z"
  },
  {
    "_id": "8bc2e168-7ebf-4719-a86d-a266b54896e0",
    "name": "AssetWatch",
    "domains": ["assetwatch.com"],
    "description": "Predictive maintenance for industrial plants using cloud-based software.",
    "primary_location": {"city": "Westerville", "state": "Ohio", "country": "United States"},
    "linkedin": "goassetwatch",
    "employee_range": "51-250",
    "_created_at": "2025-10-23T16:23:28Z",
    "_updated_at": "2026-01-28T16:20:03Z"
  },
  {
    "_id": "7747e3e3-09a8-4b0a-8f14-b70a90b1d86d",
    "name": "Truce",
    "domains": ["truce.io"],
    "description": "Analytics, Automation and ML for shippers, carriers and 3PLs",
    "primary_location": {"city": "Chicago", "state": "Illinois", "country": "United States"},
    "linkedin": "trucetech",
    "employee_range": "11-50",
    "_created_at": "2025-10-23T16:23:27Z",
    "_updated_at": "2025-10-23T16:24:29Z"
  },
  {
    "_id": "d1296e82-a1cc-4a1f-bfc0-a8ea1978d1b6",
    "name": "Primerli",
    "domains": ["primerli.com"],
    "description": "Learn any Industry in Under an Hour",
    "primary_location": {"city": "Los Angeles", "state": "California", "country": "United States"},
    "linkedin": "primerli",
    "employee_range": "1-10",
    "_created_at": "2025-10-23T16:23:27Z",
    "_updated_at": "2025-11-11T16:58:51Z"
  },
  {
    "_id": "55ecbc6b-0e7a-4144-9068-3e97cdead71e",
    "name": "The Regis Company",
    "domains": ["regiscompany.com"],
    "description": "Best-in-class learning solutions powered by simulations.",
    "primary_location": {"city": "Golden", "state": "Colorado", "country": "United States"},
    "linkedin": "the-regis-company",
    "employee_range": "51-250",
    "_created_at": "2025-10-23T16:23:27Z",
    "_updated_at": "2026-01-14T09:21:29Z"
  },
  {
    "_id": "cf9d5065-d79f-433e-8f4a-02246a32e7c7",
    "name": "The GTM Factory",
    "domains": ["thegtmfactory.com"],
    "description": "Engineers automated Go To Market workflows for SaaS teams.",
    "_created_at": "2025-10-23T16:23:27Z",
    "_updated_at": "2026-01-29T16:35:30Z"
  },
  {
    "_id": "d1236257-ad83-4f45-9391-4a6804884db3",
    "name": "FocusedEDU Staffing Group",
    "domains": ["focused-staffing.com"],
    "description": "We connect caring education professionals to those who need them most.",
    "primary_location": {"city": "Philadelphia", "state": "Pennsylvania", "country": "United States"},
    "linkedin": "focused-staffing-group",
    "employee_range": "11-50",
    "_created_at": "2025-10-23T16:23:28Z",
    "_updated_at": "2025-10-23T16:23:29Z"
  },
  {
    "_id": "2fc4926a-d98a-4553-a369-e38709ed9609",
    "name": "AdThrive",
    "domains": ["raptive.com"],
    "description": "CafeMedia and AdThrive are now Raptive, transforming creators into global brands.",
    "primary_location": {"city": "Miramar Beach", "state": "Florida", "country": "United States"},
    "linkedin": "adthrive-llc",
    "employee_range": "1-10",
    "_created_at": "2025-10-23T16:23:28Z",
    "_updated_at": "2025-10-23T16:23:30Z"
  },
  {
    "_id": "35c50d98-ca95-4753-bc93-cc8e29f8d4a4",
    "name": "TickTock AI",
    "domains": ["clockwork.io"],
    "description": "100% Software based solution to speed AI Jobs.",
    "primary_location": {"state": "California", "country": "United States"},
    "linkedin": "ticktock",
    "employee_range": "11-50",
    "_created_at": "2025-10-23T16:23:28Z",
    "_updated_at": "2025-10-23T16:23:30Z"
  },
  {
    "_id": "b637b031-6bb5-4c4a-b933-f997569bf733",
    "name": "Stephanie Holland Consulting",
    "domains": ["stephanieholland.co"],
    "linkedin": "stephanie-holland-consulting",
    "employee_range": "1-10",
    "_created_at": "2025-10-23T16:23:28Z",
    "_updated_at": "2025-10-27T08:34:47Z"
  },
  {
    "_id": "14f8080d-dca3-4a9c-8ccc-ac5aa503df8a",
    "name": "databeats.community",
    "domains": ["astorik.com"],
    "description": "The final destination for accessible data content tailored for non-data people.",
    "primary_location": {"city": "Singapore", "country": "Singapore"},
    "linkedin": "data-beats",
    "employee_range": "1-10",
    "_created_at": "2025-10-23T16:23:28Z",
    "_updated_at": "2026-01-28T16:20:03Z"
  },
  {
    "_id": "2deef24c-b56a-4707-891a-c297479fd9b1",
    "name": "ZM Url",
    "domains": ["lu.ma"],
    "description": "Organize delightful Zoom events.",
    "primary_location": {"city": "Portland", "state": "Oregon", "country": "United States"},
    "linkedin": "luma-labs-llc",
    "employee_range": "1-10",
    "_created_at": "2025-12-08T06:59:48Z",
    "_updated_at": "2025-12-08T16:15:55Z"
  }
]
